CHANGELOG.md
arend/__init__.py
arend/arend.py
arend/backends/__init__.py
arend/backends/base.py
arend/backends/mongo.py
arend/backends/redis.py
arend/brokers/__init__.py
arend/brokers/beanstalkd.py
arend/settings/__init__.py
arend/settings/arend.py
arend/settings/tasks.py
arend/worker/__init__.py
arend/worker/consumer.py
arend/worker/pool_consumers.py
arend-0.1.0.dist-info/LICENSE
arend-0.1.0.dist-info/WHEEL
arend-0.1.0.dist-info/METADATA
arend-0.1.0.dist-info/RECORD
