Metadata-Version: 2.1
Name: arend
Version: 0.1.0
Summary: A simple producer consumer library for Beanstalkd.
Home-page: https://github.com/pyprogrammerblog/arend
License: LICENSE
Author: Jose Vazquez
Author-email: josevazjim88@gmail.com
Requires-Python: >=3.9,<4.0
Classifier: License :: OSI Approved :: MIT License
Classifier: License :: Other/Proprietary License
Classifier: Operating System :: OS Independent
Classifier: Programming Language :: Python :: 3
Classifier: Programming Language :: Python :: 3.10
Classifier: Programming Language :: Python :: 3.9
Requires-Dist: PyYAML (>=6.0,<7.0)
Requires-Dist: pandas (>=1.4.3,<2.0.0)
Requires-Dist: pydantic (>=1.9.1,<2.0.0)
Requires-Dist: pymongo (>=4.2.0,<5.0.0)
Requires-Dist: pystalkd (>=1.3.0,<2.0.0)
Requires-Dist: redis (>=4.3.4,<5.0.0)
Project-URL: Documentation, https://arend.readthedocs.io/en/latest/
